sanic_redis_ext/__init__.py
sanic_redis_extension-0.1.1.dist-info/METADATA
sanic_redis_extension-0.1.1.dist-info/RECORD
sanic_redis_extension-0.1.1.dist-info/WHEEL
sanic_redis_extension-0.1.1.dist-info/top_level.txt
